{
  "type": "tconstruct:swappable_modifier",
  "allow_crystal": false,
  "conditions": [
    {
      "type": "forge:or",
      "values": [
        {
          "type": "forge:mod_loaded",
          "modid": "ad_astra"
        },
        {
          "type": "mantle:tag_filled",
          "tag": "tcompat:caps/aeronos"
        },
        {
          "type": "mantle:tag_filled",
          "tag": "tcompat:planks/aeronos"
        }
      ]
    }
  ],
  "inputs": [
    {
      "tag": "tcompat:planks/aeronos"
    },
    {
      "item": "tconstruct:pattern"
    },
    {
      "tag": "tcompat:planks/aeronos"
    }
  ],
  "result": {
    "name": "tconstruct:embellishment",
    "value": "tconstruct:wood#aeronos"
  },
  "tools": {
    "tag": "tconstruct:modifiable/embellishment/wood"
  },
  "variant_formatter": "tconstruct:material"
}