{
  "type": "tconstruct:swappable_modifier",
  "allow_crystal": false,
  "conditions": [
    {
      "type": "forge:mod_loaded",
      "modid": "biomeswevegone"
    }
  ],
  "inputs": [
    {
      "tag": "tcompat:planks/palm"
    },
    {
      "item": "tconstruct:pattern"
    },
    {
      "tag": "tcompat:planks/palm"
    }
  ],
  "result": {
    "name": "tconstruct:embellishment",
    "value": "tconstruct:wood#palm"
  },
  "tools": {
    "tag": "tconstruct:modifiable/embellishment/wood"
  },
  "variant_formatter": "tconstruct:material"
}